[
  {
    "Enabled": true,
    "Item": "SQueensJam_RtD",
    "Amount": 1,
    "CraftingStation": "piece_cauldron",
    "RepairStation": null,
    "MinStationLevel": 1,
    "Requirements": [
      {
        "Item": "Raspberry",
        "Amount": 5,
        "AmountPerLevel": 0
      },
      {
        "Item": "Blueberries",
        "Amount": 5,
        "AmountPerLevel": 0
      },
      {
        "Item": "SpiritEssense_RtD",
        "Amount": 1,
        "AmountPerLevel": 0
      }
    ]
  },
  {
    "Enabled": true,
    "Item": "SCarrotSoup_RtD",
    "Amount": 1,
    "CraftingStation": "piece_cauldron",
    "RepairStation": null,
    "MinStationLevel": 1,
    "Requirements": [
      {
        "Item": "Mushroom",
        "Amount": 1,
        "AmountPerLevel": 0
      },
      {
        "Item": "Carrot",
        "Amount": 3,
        "AmountPerLevel": 0
      },
      {
        "Item": "SpiritEssense_RtD",
        "Amount": 1,
        "AmountPerLevel": 0
      }
    ]
  },
  {
    "Enabled": true,
    "Item": "SBlackSoup_RtD",
    "Amount": 1,
    "CraftingStation": "piece_cauldron",
    "RepairStation": null,
    "MinStationLevel": 1,
    "Requirements": [
      {
        "Item": "Carrot",
        "Amount": 1,
        "AmountPerLevel": 0
      },
      {
        "Item": "Honey",
        "Amount": 1,
        "AmountPerLevel": 0
      },
      {
        "Item": "Turnip",
        "Amount": 2,
        "AmountPerLevel": 0
      },
      {
        "Item": "SpiritEssense_RtD",
        "Amount": 1,
        "AmountPerLevel": 0
      }
    ]
  },
  {
    "Enabled": true,
    "Item": "STurnipStew_RtD",
    "Amount": 1,
    "CraftingStation": "piece_cauldron",
    "RepairStation": null,
    "MinStationLevel": 1,
    "Requirements": [
      {
        "Item": "RawMeat",
        "Amount": 1,
        "AmountPerLevel": 0
      },
      {
        "Item": "Turnip",
        "Amount": 3,
        "AmountPerLevel": 0
      },
      {
        "Item": "SpiritEssense_RtD",
        "Amount": 1,
        "AmountPerLevel": 0
      }
    ]
  },
  {
    "Enabled": true,
    "Item": "SShockolateShake_RtD",
    "Amount": 1,
    "CraftingStation": "piece_cauldron",
    "RepairStation": null,
    "MinStationLevel": 1,
    "Requirements": [
      {
        "Item": "Ooze",
        "Amount": 1,
        "AmountPerLevel": 0
      },
      {
        "Item": "Raspberry",
        "Amount": 2,
        "AmountPerLevel": 0
      },
      {
        "Item": "Blueberries",
        "Amount": 2,
        "AmountPerLevel": 0
      },
      {
        "Item": "SpiritEssense_RtD",
        "Amount": 1,
        "AmountPerLevel": 0
      }
    ]
  },
  {
    "Enabled": true,
    "Item": "SOnionSoup_RtD",
    "Amount": 1,
    "CraftingStation": "piece_cauldron",
    "RepairStation": null,
    "MinStationLevel": 1,
    "Requirements": [
      {
        "Item": "Onion",
        "Amount": 3,
        "AmountPerLevel": 0
      },
      {
        "Item": "SpiritEssense_RtD",
        "Amount": 1,
        "AmountPerLevel": 0
      }
    ]
  },
  {
    "Enabled": true,
    "Item": "SEyeScream_RtD",
    "Amount": 1,
    "CraftingStation": "piece_cauldron",
    "RepairStation": null,
    "MinStationLevel": 1,
    "Requirements": [
      {
        "Item": "GreydwarfEye",
        "Amount": 3,
        "AmountPerLevel": 0
      },
      {
        "Item": "FreezeGland",
        "Amount": 1,
        "AmountPerLevel": 0
      },
      {
        "Item": "SpiritEssense_RtD",
        "Amount": 1,
        "AmountPerLevel": 0
      }
    ]
  },
  {
    "Enabled": true,
    "Item": "SBloodPudding_RtD",
    "Amount": 1,
    "CraftingStation": "piece_cauldron",
    "RepairStation": null,
    "MinStationLevel": 1,
    "Requirements": [
      {
        "Item": "Thistle",
        "Amount": 2,
        "AmountPerLevel": 0
      },
      {
        "Item": "Bloodbag",
        "Amount": 2,
        "AmountPerLevel": 0
      },
      {
        "Item": "BarleyFlour",
        "Amount": 4,
        "AmountPerLevel": 0
      },
      {
        "Item": "SpiritEssense_RtD",
        "Amount": 1,
        "AmountPerLevel": 0
      }
    ]
  }
]